lesionprocessor/__init__.py
lesionprocessor/__main__.py
lesionprocessor/lesion.py
lesionprocessor/processor.py
lesionprocessor/cmdpattern/__init__.py
lesionprocessor/cmdpattern/commands.py
lesionprocessor/cmdpattern/invokers.py
lesionprocessor/cmdpattern/receivers.py
lesionprocessor/helpers/__init__.py
lesionprocessor/helpers/constants.py
lesionprocessor/helpers/utils.py
lesionprocessor-0.1.0.dist-info/METADATA
lesionprocessor-0.1.0.dist-info/RECORD
lesionprocessor-0.1.0.dist-info/WHEEL
lesionprocessor-0.1.0.dist-info/top_level.txt
