Metadata-Version: 2.1
Name: lesionprocessor
Version: 0.1.0
Summary: Crops or labels lesion(s) shown in an image.
Home-page: https://github.com/marsbound/lesion-processor
Author: Clark Lee
Author-email: marsbound@pm.me
License: Apache License 2.0
Platform: UNKNOWN
Classifier: Programming Language :: Python :: 3.6
Requires-Python: <=3.6,>=3
Requires-Dist: opencv-python
Requires-Dist: numpy
Requires-Dist: tqdm
Requires-Dist: pathos
